{
	"start":	{
		"connected":	[{
				"socket":	5,
				"local_host":	"172.20.171.186",
				"local_port":	60964,
				"remote_host":	"54.227.41.78",
				"remote_port":	5201
			}],
		"version":	"iperf 3.16",
		"system_info":	"Linux DESKTOP-OR35M89 6.18.33.1-microsoft-standard-WSL2 #1 SMP PREEMPT_DYNAMIC Fri Jun  5 01:12:21 UTC 2026 x86_64",
		"timestamp":	{
			"time":	"Thu, 25 Jun 2026 23:31:41 GMT",
			"timesecs":	1782430301
		},
		"connecting_to":	{
			"host":	"54.227.41.78",
			"port":	5201
		},
		"cookie":	"adoj5l46zgbobbbt352guuwf7yqbvlxmltle",
		"tcp_mss_default":	1448,
		"target_bitrate":	100000000,
		"fq_rate":	0,
		"sock_bufsize":	0,
		"sndbuf_actual":	16384,
		"rcvbuf_actual":	131072,
		"test_start":	{
			"protocol":	"TCP",
			"num_streams":	1,
			"blksize":	131072,
			"omit":	0,
			"duration":	30,
			"bytes":	0,
			"blocks":	0,
			"reverse":	0,
			"tos":	0,
			"target_bitrate":	100000000,
			"bidir":	0,
			"fqrate":	0
		}
	},
	"intervals":	[{
			"streams":	[{
					"socket":	5,
					"start":	0,
					"end":	1.000165,
					"seconds":	1.0001649856567383,
					"bytes":	131072,
					"bits_per_second":	1048403.0285378103,
					"retransmits":	5,
					"snd_cwnd":	1448,
					"snd_wnd":	137856,
					"rtt":	105374,
					"rttvar":	13245,
					"pmtu":	1500,
					"omitted":	false,
					"sender":	true
				}],
			"sum":	{
				"start":	0,
				"end":	1.000165,
				"seconds":	1.0001649856567383,
				"bytes":	131072,
				"bits_per_second":	1048403.0285378103,
				"retransmits":	5,
				"omitted":	false,
				"sender":	true
			}
		}, {
			"streams":	[{
					"socket":	5,
					"start":	1.000165,
					"end":	2.00015,
					"seconds":	0.9999849796295166,
					"bytes":	0,
					"bits_per_second":	0,
					"retransmits":	8,
					"snd_cwnd":	2896,
					"snd_wnd":	136448,
					"rtt":	99332,
					"rttvar":	3447,
					"pmtu":	1500,
					"omitted":	false,
					"sender":	true
				}],
			"sum":	{
				"start":	1.000165,
				"end":	2.00015,
				"seconds":	0.9999849796295166,
				"bytes":	0,
				"bits_per_second":	0,
				"retransmits":	8,
				"omitted":	false,
				"sender":	true
			}
		}, {
			"streams":	[{
					"socket":	5,
					"start":	2.00015,
					"end":	3.000149,
					"seconds":	0.99999898672103882,
					"bytes":	0,
					"bits_per_second":	0,
					"retransmits":	3,
					"snd_cwnd":	4344,
					"snd_wnd":	133632,
					"rtt":	108604,
					"rttvar":	18351,
					"pmtu":	1500,
					"omitted":	false,
					"sender":	true
				}],
			"sum":	{
				"start":	2.00015,
				"end":	3.000149,
				"seconds":	0.99999898672103882,
				"bytes":	0,
				"bits_per_second":	0,
				"retransmits":	3,
				"omitted":	false,
				"sender":	true
			}
		}, {
			"streams":	[{
					"socket":	5,
					"start":	3.000149,
					"end":	4.000145,
					"seconds":	0.9999960064888,
					"bytes":	131072,
					"bits_per_second":	1048580.1875167228,
					"retransmits":	2,
					"snd_cwnd":	5792,
					"snd_wnd":	130048,
					"rtt":	103019,
					"rttvar":	9526,
					"pmtu":	1500,
					"omitted":	false,
					"sender":	true
				}],
			"sum":	{
				"start":	3.000149,
				"end":	4.000145,
				"seconds":	0.9999960064888,
				"bytes":	131072,
				"bits_per_second":	1048580.1875167228,
				"retransmits":	2,
				"omitted":	false,
				"sender":	true
			}
		}, {
			"streams":	[{
					"socket":	5,
					"start":	4.000145,
					"end":	5.000103,
					"seconds":	0.99995797872543335,
					"bytes":	0,
					"bits_per_second":	0,
					"retransmits":	0,
					"snd_cwnd":	11584,
					"snd_wnd":	136448,
					"rtt":	107294,
					"rttvar":	13664,
					"pmtu":	1500,
					"omitted":	false,
					"sender":	true
				}],
			"sum":	{
				"start":	4.000145,
				"end":	5.000103,
				"seconds":	0.99995797872543335,
				"bytes":	0,
				"bits_per_second":	0,
				"retransmits":	0,
				"omitted":	false,
				"sender":	true
			}
		}, {
			"streams":	[{
					"socket":	5,
					"start":	5.000103,
					"end":	6.000142,
					"seconds":	1.0000389814376831,
					"bytes":	131072,
					"bits_per_second":	1048535.1265933041,
					"retransmits":	2,
					"snd_cwnd":	13032,
					"snd_wnd":	136448,
					"rtt":	109165,
					"rttvar":	16147,
					"pmtu":	1500,
					"omitted":	false,
					"sender":	true
				}],
			"sum":	{
				"start":	5.000103,
				"end":	6.000142,
				"seconds":	1.0000389814376831,
				"bytes":	131072,
				"bits_per_second":	1048535.1265933041,
				"retransmits":	2,
				"omitted":	false,
				"sender":	true
			}
		}, {
			"streams":	[{
					"socket":	5,
					"start":	6.000142,
					"end":	7.000098,
					"seconds":	0.99995601177215576,
					"bytes":	131072,
					"bits_per_second":	1048622.1270290462,
					"retransmits":	5,
					"snd_cwnd":	5792,
					"snd_wnd":	137856,
					"rtt":	116992,
					"rttvar":	25998,
					"pmtu":	1500,
					"omitted":	false,
					"sender":	true
				}],
			"sum":	{
				"start":	6.000142,
				"end":	7.000098,
				"seconds":	0.99995601177215576,
				"bytes":	131072,
				"bits_per_second":	1048622.1270290462,
				"retransmits":	5,
				"omitted":	false,
				"sender":	true
			}
		}, {
			"streams":	[{
					"socket":	5,
					"start":	7.000098,
					"end":	8.000097,
					"seconds":	0.99999898672103882,
					"bytes":	0,
					"bits_per_second":	0,
					"retransmits":	3,
					"snd_cwnd":	4344,
					"snd_wnd":	136448,
					"rtt":	110642,
					"rttvar":	18629,
					"pmtu":	1500,
					"omitted":	false,
					"sender":	true
				}],
			"sum":	{
				"start":	7.000098,
				"end":	8.000097,
				"seconds":	0.99999898672103882,
				"bytes":	0,
				"bits_per_second":	0,
				"retransmits":	3,
				"omitted":	false,
				"sender":	true
			}
		}, {
			"streams":	[{
					"socket":	5,
					"start":	8.000097,
					"end":	9.000154,
					"seconds":	1.0000569820404053,
					"bytes":	0,
					"bits_per_second":	0,
					"retransmits":	2,
					"snd_cwnd":	5792,
					"snd_wnd":	137856,
					"rtt":	114324,
					"rttvar":	23273,
					"pmtu":	1500,
					"omitted":	false,
					"sender":	true
				}],
			"sum":	{
				"start":	8.000097,
				"end":	9.000154,
				"seconds":	1.0000569820404053,
				"bytes":	0,
				"bits_per_second":	0,
				"retransmits":	2,
				"omitted":	false,
				"sender":	true
			}
		}, {
			"streams":	[{
					"socket":	5,
					"start":	9.000154,
					"end":	10.000152,
					"seconds":	0.99999797344207764,
					"bytes":	0,
					"bits_per_second":	0,
					"retransmits":	3,
					"snd_cwnd":	4344,
					"snd_wnd":	136448,
					"rtt":	116644,
					"rttvar":	27334,
					"pmtu":	1500,
					"omitted":	false,
					"sender":	true
				}],
			"sum":	{
				"start":	9.000154,
				"end":	10.000152,
				"seconds":	0.99999797344207764,
				"bytes":	0,
				"bits_per_second":	0,
				"retransmits":	3,
				"omitted":	false,
				"sender":	true
			}
		}, {
			"streams":	[{
					"socket":	5,
					"start":	10.000152,
					"end":	11.00015,
					"seconds":	0.99999797344207764,
					"bytes":	131072,
					"bits_per_second":	1048578.1250043064,
					"retransmits":	3,
					"snd_cwnd":	2896,
					"snd_wnd":	137856,
					"rtt":	108167,
					"rttvar":	17099,
					"pmtu":	1500,
					"omitted":	false,
					"sender":	true
				}],
			"sum":	{
				"start":	10.000152,
				"end":	11.00015,
				"seconds":	0.99999797344207764,
				"bytes":	131072,
				"bits_per_second":	1048578.1250043064,
				"retransmits":	3,
				"omitted":	false,
				"sender":	true
			}
		}, {
			"streams":	[{
					"socket":	5,
					"start":	11.00015,
					"end":	12.000122,
					"seconds":	0.99997198581695557,
					"bytes":	0,
					"bits_per_second":	0,
					"retransmits":	4,
					"snd_cwnd":	1448,
					"snd_wnd":	136448,
					"rtt":	97690,
					"rttvar":	1750,
					"pmtu":	1500,
					"omitted":	false,
					"sender":	true
				}],
			"sum":	{
				"start":	11.00015,
				"end":	12.000122,
				"seconds":	0.99997198581695557,
				"bytes":	0,
				"bits_per_second":	0,
				"retransmits":	4,
				"omitted":	false,
				"sender":	true
			}
		}, {
			"streams":	[{
					"socket":	5,
					"start":	12.000122,
					"end":	13.000147,
					"seconds":	1.0000250339508057,
					"bytes":	0,
					"bits_per_second":	0,
					"retransmits":	2,
					"snd_cwnd":	5792,
					"snd_wnd":	136448,
					"rtt":	98325,
					"rttvar":	1006,
					"pmtu":	1500,
					"omitted":	false,
					"sender":	true
				}],
			"sum":	{
				"start":	12.000122,
				"end":	13.000147,
				"seconds":	1.0000250339508057,
				"bytes":	0,
				"bits_per_second":	0,
				"retransmits":	2,
				"omitted":	false,
				"sender":	true
			}
		}, {
			"streams":	[{
					"socket":	5,
					"start":	13.000147,
					"end":	14.000155,
					"seconds":	1.0000079870224,
					"bytes":	0,
					"bits_per_second":	0,
					"retransmits":	3,
					"snd_cwnd":	2896,
					"snd_wnd":	132608,
					"rtt":	112219,
					"rttvar":	22465,
					"pmtu":	1500,
					"omitted":	false,
					"sender":	true
				}],
			"sum":	{
				"start":	13.000147,
				"end":	14.000155,
				"seconds":	1.0000079870224,
				"bytes":	0,
				"bits_per_second":	0,
				"retransmits":	3,
				"omitted":	false,
				"sender":	true
			}
		}, {
			"streams":	[{
					"socket":	5,
					"start":	14.000155,
					"end":	15.000147,
					"seconds":	0.9999920129776,
					"bytes":	131072,
					"bits_per_second":	1048584.3750668918,
					"retransmits":	4,
					"snd_cwnd":	5792,
					"snd_wnd":	136448,
					"rtt":	105566,
					"rttvar":	13563,
					"pmtu":	1500,
					"omitted":	false,
					"sender":	true
				}],
			"sum":	{
				"start":	14.000155,
				"end":	15.000147,
				"seconds":	0.9999920129776,
				"bytes":	131072,
				"bits_per_second":	1048584.3750668918,
				"retransmits":	4,
				"omitted":	false,
				"sender":	true
			}
		}, {
			"streams":	[{
					"socket":	5,
					"start":	15.000147,
					"end":	16.000144,
					"seconds":	0.99999701976776123,
					"bytes":	0,
					"bits_per_second":	0,
					"retransmits":	3,
					"snd_cwnd":	5792,
					"snd_wnd":	137856,
					"rtt":	105840,
					"rttvar":	12483,
					"pmtu":	1500,
					"omitted":	false,
					"sender":	true
				}],
			"sum":	{
				"start":	15.000147,
				"end":	16.000144,
				"seconds":	0.99999701976776123,
				"bytes":	0,
				"bits_per_second":	0,
				"retransmits":	3,
				"omitted":	false,
				"sender":	true
			}
		}, {
			"streams":	[{
					"socket":	5,
					"start":	16.000144,
					"end":	17.000141,
					"seconds":	0.99999701976776123,
					"bytes":	0,
					"bits_per_second":	0,
					"retransmits":	6,
					"snd_cwnd":	1448,
					"snd_wnd":	136448,
					"rtt":	101002,
					"rttvar":	5641,
					"pmtu":	1500,
					"omitted":	false,
					"sender":	true
				}],
			"sum":	{
				"start":	16.000144,
				"end":	17.000141,
				"seconds":	0.99999701976776123,
				"bytes":	0,
				"bits_per_second":	0,
				"retransmits":	6,
				"omitted":	false,
				"sender":	true
			}
		}, {
			"streams":	[{
					"socket":	5,
					"start":	17.000141,
					"end":	18.000128,
					"seconds":	0.999987006187439,
					"bytes":	131072,
					"bits_per_second":	1048589.625177043,
					"retransmits":	2,
					"snd_cwnd":	4344,
					"snd_wnd":	136448,
					"rtt":	106336,
					"rttvar":	13556,
					"pmtu":	1500,
					"omitted":	false,
					"sender":	true
				}],
			"sum":	{
				"start":	17.000141,
				"end":	18.000128,
				"seconds":	0.999987006187439,
				"bytes":	131072,
				"bits_per_second":	1048589.625177043,
				"retransmits":	2,
				"omitted":	false,
				"sender":	true
			}
		}, {
			"streams":	[{
					"socket":	5,
					"start":	18.000128,
					"end":	19.000212,
					"seconds":	1.0000840425491333,
					"bytes":	0,
					"bits_per_second":	0,
					"retransmits":	4,
					"snd_cwnd":	2896,
					"snd_wnd":	136448,
					"rtt":	98863,
					"rttvar":	2643,
					"pmtu":	1500,
					"omitted":	false,
					"sender":	true
				}],
			"sum":	{
				"start":	18.000128,
				"end":	19.000212,
				"seconds":	1.0000840425491333,
				"bytes":	0,
				"bits_per_second":	0,
				"retransmits":	4,
				"omitted":	false,
				"sender":	true
			}
		}, {
			"streams":	[{
					"socket":	5,
					"start":	19.000212,
					"end":	20.000117,
					"seconds":	0.999904990196228,
					"bytes":	0,
					"bits_per_second":	0,
					"retransmits":	2,
					"snd_cwnd":	5792,
					"snd_wnd":	136448,
					"rtt":	105114,
					"rttvar":	11721,
					"pmtu":	1500,
					"omitted":	false,
					"sender":	true
				}],
			"sum":	{
				"start":	19.000212,
				"end":	20.000117,
				"seconds":	0.999904990196228,
				"bytes":	0,
				"bits_per_second":	0,
				"retransmits":	2,
				"omitted":	false,
				"sender":	true
			}
		}, {
			"streams":	[{
					"socket":	5,
					"start":	20.000117,
					"end":	21.00052,
					"seconds":	1.0004030466079712,
					"bytes":	0,
					"bits_per_second":	0,
					"retransmits":	3,
					"snd_cwnd":	4344,
					"snd_wnd":	128768,
					"rtt":	100428,
					"rttvar":	2578,
					"pmtu":	1500,
					"omitted":	false,
					"sender":	true
				}],
			"sum":	{
				"start":	20.000117,
				"end":	21.00052,
				"seconds":	1.0004030466079712,
				"bytes":	0,
				"bits_per_second":	0,
				"retransmits":	3,
				"omitted":	false,
				"sender":	true
			}
		}, {
			"streams":	[{
					"socket":	5,
					"start":	21.00052,
					"end":	22.000526,
					"seconds":	1.0000059604644775,
					"bytes":	131072,
					"bits_per_second":	1048569.7500372527,
					"retransmits":	4,
					"snd_cwnd":	2896,
					"snd_wnd":	131328,
					"rtt":	99280,
					"rttvar":	3483,
					"pmtu":	1500,
					"omitted":	false,
					"sender":	true
				}],
			"sum":	{
				"start":	21.00052,
				"end":	22.000526,
				"seconds":	1.0000059604644775,
				"bytes":	131072,
				"bits_per_second":	1048569.7500372527,
				"retransmits":	4,
				"omitted":	false,
				"sender":	true
			}
		}, {
			"streams":	[{
					"socket":	5,
					"start":	22.000526,
					"end":	23.000493,
					"seconds":	0.99996697902679443,
					"bytes":	0,
					"bits_per_second":	0,
					"retransmits":	3,
					"snd_cwnd":	2896,
					"snd_wnd":	137856,
					"rtt":	106393,
					"rttvar":	15158,
					"pmtu":	1500,
					"omitted":	false,
					"sender":	true
				}],
			"sum":	{
				"start":	22.000526,
				"end":	23.000493,
				"seconds":	0.99996697902679443,
				"bytes":	0,
				"bits_per_second":	0,
				"retransmits":	3,
				"omitted":	false,
				"sender":	true
			}
		}, {
			"streams":	[{
					"socket":	5,
					"start":	23.000493,
					"end":	24.0005,
					"seconds":	1.0000070333480835,
					"bytes":	0,
					"bits_per_second":	0,
					"retransmits":	0,
					"snd_cwnd":	8688,
					"snd_wnd":	137856,
					"rtt":	108004,
					"rttvar":	15288,
					"pmtu":	1500,
					"omitted":	false,
					"sender":	true
				}],
			"sum":	{
				"start":	23.000493,
				"end":	24.0005,
				"seconds":	1.0000070333480835,
				"bytes":	0,
				"bits_per_second":	0,
				"retransmits":	0,
				"omitted":	false,
				"sender":	true
			}
		}, {
			"streams":	[{
					"socket":	5,
					"start":	24.0005,
					"end":	25.000155,
					"seconds":	0.99965500831604,
					"bytes":	0,
					"bits_per_second":	0,
					"retransmits":	5,
					"snd_cwnd":	4344,
					"snd_wnd":	137856,
					"rtt":	101873,
					"rttvar":	6619,
					"pmtu":	1500,
					"omitted":	false,
					"sender":	true
				}],
			"sum":	{
				"start":	24.0005,
				"end":	25.000155,
				"seconds":	0.99965500831604,
				"bytes":	0,
				"bits_per_second":	0,
				"retransmits":	5,
				"omitted":	false,
				"sender":	true
			}
		}, {
			"streams":	[{
					"socket":	5,
					"start":	25.000155,
					"end":	26.000496,
					"seconds":	1.0003410577774048,
					"bytes":	131072,
					"bits_per_second":	1048218.4969292027,
					"retransmits":	1,
					"snd_cwnd":	8688,
					"snd_wnd":	137856,
					"rtt":	112267,
					"rttvar":	19704,
					"pmtu":	1500,
					"omitted":	false,
					"sender":	true
				}],
			"sum":	{
				"start":	25.000155,
				"end":	26.000496,
				"seconds":	1.0003410577774048,
				"bytes":	131072,
				"bits_per_second":	1048218.4969292027,
				"retransmits":	1,
				"omitted":	false,
				"sender":	true
			}
		}, {
			"streams":	[{
					"socket":	5,
					"start":	26.000496,
					"end":	27.000112,
					"seconds":	0.999616026878357,
					"bytes":	131072,
					"bits_per_second":	1048978.779656562,
					"retransmits":	6,
					"snd_cwnd":	5792,
					"snd_wnd":	132608,
					"rtt":	103544,
					"rttvar":	10616,
					"pmtu":	1500,
					"omitted":	false,
					"sender":	true
				}],
			"sum":	{
				"start":	26.000496,
				"end":	27.000112,
				"seconds":	0.999616026878357,
				"bytes":	131072,
				"bits_per_second":	1048978.779656562,
				"retransmits":	6,
				"omitted":	false,
				"sender":	true
			}
		}, {
			"streams":	[{
					"socket":	5,
					"start":	27.000112,
					"end":	28.000283,
					"seconds":	1.0001709461212158,
					"bytes":	0,
					"bits_per_second":	0,
					"retransmits":	4,
					"snd_cwnd":	5792,
					"snd_wnd":	137856,
					"rtt":	108780,
					"rttvar":	17673,
					"pmtu":	1500,
					"omitted":	false,
					"sender":	true
				}],
			"sum":	{
				"start":	27.000112,
				"end":	28.000283,
				"seconds":	1.0001709461212158,
				"bytes":	0,
				"bits_per_second":	0,
				"retransmits":	4,
				"omitted":	false,
				"sender":	true
			}
		}, {
			"streams":	[{
					"socket":	5,
					"start":	28.000283,
					"end":	29.000171,
					"seconds":	0.999888002872467,
					"bytes":	0,
					"bits_per_second":	0,
					"retransmits":	6,
					"snd_cwnd":	2896,
					"snd_wnd":	134912,
					"rtt":	105493,
					"rttvar":	14299,
					"pmtu":	1500,
					"omitted":	false,
					"sender":	true
				}],
			"sum":	{
				"start":	28.000283,
				"end":	29.000171,
				"seconds":	0.999888002872467,
				"bytes":	0,
				"bits_per_second":	0,
				"retransmits":	6,
				"omitted":	false,
				"sender":	true
			}
		}, {
			"streams":	[{
					"socket":	5,
					"start":	29.000171,
					"end":	30.00093,
					"seconds":	1.00075900554657,
					"bytes":	0,
					"bits_per_second":	0,
					"retransmits":	0,
					"snd_cwnd":	8688,
					"snd_wnd":	136448,
					"rtt":	109900,
					"rttvar":	18044,
					"pmtu":	1500,
					"omitted":	false,
					"sender":	true
				}],
			"sum":	{
				"start":	29.000171,
				"end":	30.00093,
				"seconds":	1.00075900554657,
				"bytes":	0,
				"bits_per_second":	0,
				"retransmits":	0,
				"omitted":	false,
				"sender":	true
			}
		}],
	"end":	{
		"streams":	[{
				"sender":	{
					"socket":	5,
					"start":	0,
					"end":	30.00093,
					"seconds":	30.00093,
					"bytes":	1310720,
					"bits_per_second":	349514.49838388345,
					"retransmits":	98,
					"max_snd_cwnd":	13032,
					"max_snd_wnd":	137856,
					"max_rtt":	116992,
					"min_rtt":	97690,
					"mean_rtt":	106215,
					"sender":	true
				},
				"receiver":	{
					"socket":	5,
					"start":	0,
					"end":	30.096063,
					"seconds":	30.00093,
					"bytes":	1310720,
					"bits_per_second":	348409.6906628618,
					"sender":	true
				}
			}],
		"sum_sent":	{
			"start":	0,
			"end":	30.00093,
			"seconds":	30.00093,
			"bytes":	1310720,
			"bits_per_second":	349514.49838388345,
			"retransmits":	98,
			"sender":	true
		},
		"sum_received":	{
			"start":	0,
			"end":	30.096063,
			"seconds":	30.096063,
			"bytes":	1310720,
			"bits_per_second":	348409.6906628618,
			"sender":	true
		},
		"cpu_utilization_percent":	{
			"host_total":	3.0494180657271408,
			"host_user":	0.57463946312043368,
			"host_system":	2.4747720203285759,
			"remote_total":	0.11910852319220412,
			"remote_user":	0.03524046634241406,
			"remote_system":	0.0838647341582624
		},
		"sender_tcp_congestion":	"cubic",
		"receiver_tcp_congestion":	"cubic"
	}
}
