{
	"start":	{
		"connected":	[{
				"socket":	5,
				"local_host":	"172.20.171.186",
				"local_port":	40290,
				"remote_host":	"54.227.41.78",
				"remote_port":	5201
			}],
		"version":	"iperf 3.16",
		"system_info":	"Linux DESKTOP-OR35M89 6.18.33.1-microsoft-standard-WSL2 #1 SMP PREEMPT_DYNAMIC Fri Jun  5 01:12:21 UTC 2026 x86_64",
		"timestamp":	{
			"time":	"Thu, 25 Jun 2026 22:24:29 GMT",
			"timesecs":	1782426269
		},
		"connecting_to":	{
			"host":	"54.227.41.78",
			"port":	5201
		},
		"cookie":	"hlrali5z6mwovvlztv3f76khrxazukf4q5e2",
		"tcp_mss_default":	1448,
		"target_bitrate":	100000000,
		"fq_rate":	0,
		"sock_bufsize":	0,
		"sndbuf_actual":	16384,
		"rcvbuf_actual":	131072,
		"test_start":	{
			"protocol":	"TCP",
			"num_streams":	1,
			"blksize":	131072,
			"omit":	0,
			"duration":	30,
			"bytes":	0,
			"blocks":	0,
			"reverse":	0,
			"tos":	0,
			"target_bitrate":	100000000,
			"bidir":	0,
			"fqrate":	0
		}
	},
	"intervals":	[{
			"streams":	[{
					"socket":	5,
					"start":	0,
					"end":	1.000505,
					"seconds":	1.0005049705505371,
					"bytes":	262144,
					"bits_per_second":	2096093.5344939095,
					"retransmits":	5,
					"snd_cwnd":	15928,
					"snd_wnd":	155136,
					"rtt":	101753,
					"rttvar":	1144,
					"pmtu":	1500,
					"omitted":	false,
					"sender":	true
				}],
			"sum":	{
				"start":	0,
				"end":	1.000505,
				"seconds":	1.0005049705505371,
				"bytes":	262144,
				"bits_per_second":	2096093.5344939095,
				"retransmits":	5,
				"omitted":	false,
				"sender":	true
			}
		}, {
			"streams":	[{
					"socket":	5,
					"start":	1.000505,
					"end":	2.000586,
					"seconds":	1.000080943107605,
					"bytes":	131072,
					"bits_per_second":	1048491.1318694903,
					"retransmits":	6,
					"snd_cwnd":	10136,
					"snd_wnd":	146944,
					"rtt":	101566,
					"rttvar":	2295,
					"pmtu":	1500,
					"omitted":	false,
					"sender":	true
				}],
			"sum":	{
				"start":	1.000505,
				"end":	2.000586,
				"seconds":	1.000080943107605,
				"bytes":	131072,
				"bits_per_second":	1048491.1318694903,
				"retransmits":	6,
				"omitted":	false,
				"sender":	true
			}
		}, {
			"streams":	[{
					"socket":	5,
					"start":	2.000586,
					"end":	3.000529,
					"seconds":	0.99994301795959473,
					"bytes":	131072,
					"bits_per_second":	1048635.7534048709,
					"retransmits":	1,
					"snd_cwnd":	11584,
					"snd_wnd":	155136,
					"rtt":	117692,
					"rttvar":	21198,
					"pmtu":	1500,
					"omitted":	false,
					"sender":	true
				}],
			"sum":	{
				"start":	2.000586,
				"end":	3.000529,
				"seconds":	0.99994301795959473,
				"bytes":	131072,
				"bits_per_second":	1048635.7534048709,
				"retransmits":	1,
				"omitted":	false,
				"sender":	true
			}
		}, {
			"streams":	[{
					"socket":	5,
					"start":	3.000529,
					"end":	4.000534,
					"seconds":	1.0000050067901611,
					"bytes":	131072,
					"bits_per_second":	1048570.7500262855,
					"retransmits":	3,
					"snd_cwnd":	8688,
					"snd_wnd":	156672,
					"rtt":	111289,
					"rttvar":	13386,
					"pmtu":	1500,
					"omitted":	false,
					"sender":	true
				}],
			"sum":	{
				"start":	3.000529,
				"end":	4.000534,
				"seconds":	1.0000050067901611,
				"bytes":	131072,
				"bits_per_second":	1048570.7500262855,
				"retransmits":	3,
				"omitted":	false,
				"sender":	true
			}
		}, {
			"streams":	[{
					"socket":	5,
					"start":	4.000534,
					"end":	5.000544,
					"seconds":	1.0000100135803223,
					"bytes":	0,
					"bits_per_second":	0,
					"retransmits":	4,
					"snd_cwnd":	10136,
					"snd_wnd":	156672,
					"rtt":	102932,
					"rttvar":	4617,
					"pmtu":	1500,
					"omitted":	false,
					"sender":	true
				}],
			"sum":	{
				"start":	4.000534,
				"end":	5.000544,
				"seconds":	1.0000100135803223,
				"bytes":	0,
				"bits_per_second":	0,
				"retransmits":	4,
				"omitted":	false,
				"sender":	true
			}
		}, {
			"streams":	[{
					"socket":	5,
					"start":	5.000544,
					"end":	6.000543,
					"seconds":	0.99999898672103882,
					"bytes":	131072,
					"bits_per_second":	1048577.0625010766,
					"retransmits":	4,
					"snd_cwnd":	5792,
					"snd_wnd":	155136,
					"rtt":	102024,
					"rttvar":	2409,
					"pmtu":	1500,
					"omitted":	false,
					"sender":	true
				}],
			"sum":	{
				"start":	5.000544,
				"end":	6.000543,
				"seconds":	0.99999898672103882,
				"bytes":	131072,
				"bits_per_second":	1048577.0625010766,
				"retransmits":	4,
				"omitted":	false,
				"sender":	true
			}
		}, {
			"streams":	[{
					"socket":	5,
					"start":	6.000543,
					"end":	7.000595,
					"seconds":	1.0000519752502441,
					"bytes":	0,
					"bits_per_second":	0,
					"retransmits":	2,
					"snd_cwnd":	2896,
					"snd_wnd":	148352,
					"rtt":	107261,
					"rttvar":	13330,
					"pmtu":	1500,
					"omitted":	false,
					"sender":	true
				}],
			"sum":	{
				"start":	6.000543,
				"end":	7.000595,
				"seconds":	1.0000519752502441,
				"bytes":	0,
				"bits_per_second":	0,
				"retransmits":	2,
				"omitted":	false,
				"sender":	true
			}
		}, {
			"streams":	[{
					"socket":	5,
					"start":	7.000595,
					"end":	8.000542,
					"seconds":	0.99994701147079468,
					"bytes":	131072,
					"bits_per_second":	1048631.5654443312,
					"retransmits":	0,
					"snd_cwnd":	8688,
					"snd_wnd":	156672,
					"rtt":	113070,
					"rttvar":	16448,
					"pmtu":	1500,
					"omitted":	false,
					"sender":	true
				}],
			"sum":	{
				"start":	7.000595,
				"end":	8.000542,
				"seconds":	0.99994701147079468,
				"bytes":	131072,
				"bits_per_second":	1048631.5654443312,
				"retransmits":	0,
				"omitted":	false,
				"sender":	true
			}
		}, {
			"streams":	[{
					"socket":	5,
					"start":	8.000542,
					"end":	9.000539,
					"seconds":	0.99999701976776123,
					"bytes":	0,
					"bits_per_second":	0,
					"retransmits":	2,
					"snd_cwnd":	8688,
					"snd_wnd":	156672,
					"rtt":	113268,
					"rttvar":	18003,
					"pmtu":	1500,
					"omitted":	false,
					"sender":	true
				}],
			"sum":	{
				"start":	8.000542,
				"end":	9.000539,
				"seconds":	0.99999701976776123,
				"bytes":	0,
				"bits_per_second":	0,
				"retransmits":	2,
				"omitted":	false,
				"sender":	true
			}
		}, {
			"streams":	[{
					"socket":	5,
					"start":	9.000539,
					"end":	10.000598,
					"seconds":	1.0000590085983276,
					"bytes":	0,
					"bits_per_second":	0,
					"retransmits":	0,
					"snd_cwnd":	15928,
					"snd_wnd":	156672,
					"rtt":	104188,
					"rttvar":	4753,
					"pmtu":	1500,
					"omitted":	false,
					"sender":	true
				}],
			"sum":	{
				"start":	9.000539,
				"end":	10.000598,
				"seconds":	1.0000590085983276,
				"bytes":	0,
				"bits_per_second":	0,
				"retransmits":	0,
				"omitted":	false,
				"sender":	true
			}
		}, {
			"streams":	[{
					"socket":	5,
					"start":	10.000598,
					"end":	11.000525,
					"seconds":	0.99992698431015,
					"bytes":	262144,
					"bits_per_second":	2097305.1361813438,
					"retransmits":	4,
					"snd_cwnd":	15928,
					"snd_wnd":	156672,
					"rtt":	104129,
					"rttvar":	4502,
					"pmtu":	1500,
					"omitted":	false,
					"sender":	true
				}],
			"sum":	{
				"start":	10.000598,
				"end":	11.000525,
				"seconds":	0.99992698431015,
				"bytes":	262144,
				"bits_per_second":	2097305.1361813438,
				"retransmits":	4,
				"omitted":	false,
				"sender":	true
			}
		}, {
			"streams":	[{
					"socket":	5,
					"start":	11.000525,
					"end":	12.000545,
					"seconds":	1.0000200271606445,
					"bytes":	0,
					"bits_per_second":	0,
					"retransmits":	3,
					"snd_cwnd":	7240,
					"snd_wnd":	156672,
					"rtt":	106556,
					"rttvar":	13240,
					"pmtu":	1500,
					"omitted":	false,
					"sender":	true
				}],
			"sum":	{
				"start":	11.000525,
				"end":	12.000545,
				"seconds":	1.0000200271606445,
				"bytes":	0,
				"bits_per_second":	0,
				"retransmits":	3,
				"omitted":	false,
				"sender":	true
			}
		}, {
			"streams":	[{
					"socket":	5,
					"start":	12.000545,
					"end":	13.000525,
					"seconds":	0.99997997283935547,
					"bytes":	262144,
					"bits_per_second":	2097194.0008411575,
					"retransmits":	3,
					"snd_cwnd":	7240,
					"snd_wnd":	155136,
					"rtt":	100654,
					"rttvar":	4830,
					"pmtu":	1500,
					"omitted":	false,
					"sender":	true
				}],
			"sum":	{
				"start":	12.000545,
				"end":	13.000525,
				"seconds":	0.99997997283935547,
				"bytes":	262144,
				"bits_per_second":	2097194.0008411575,
				"retransmits":	3,
				"omitted":	false,
				"sender":	true
			}
		}, {
			"streams":	[{
					"socket":	5,
					"start":	13.000525,
					"end":	14.000535,
					"seconds":	1.0000100135803223,
					"bytes":	0,
					"bits_per_second":	0,
					"retransmits":	2,
					"snd_cwnd":	8688,
					"snd_wnd":	155136,
					"rtt":	102119,
					"rttvar":	5548,
					"pmtu":	1500,
					"omitted":	false,
					"sender":	true
				}],
			"sum":	{
				"start":	13.000525,
				"end":	14.000535,
				"seconds":	1.0000100135803223,
				"bytes":	0,
				"bits_per_second":	0,
				"retransmits":	2,
				"omitted":	false,
				"sender":	true
			}
		}, {
			"streams":	[{
					"socket":	5,
					"start":	14.000535,
					"end":	15.000531,
					"seconds":	0.9999960064888,
					"bytes":	0,
					"bits_per_second":	0,
					"retransmits":	1,
					"snd_cwnd":	10136,
					"snd_wnd":	156672,
					"rtt":	102022,
					"rttvar":	4593,
					"pmtu":	1500,
					"omitted":	false,
					"sender":	true
				}],
			"sum":	{
				"start":	14.000535,
				"end":	15.000531,
				"seconds":	0.9999960064888,
				"bytes":	0,
				"bits_per_second":	0,
				"retransmits":	1,
				"omitted":	false,
				"sender":	true
			}
		}, {
			"streams":	[{
					"socket":	5,
					"start":	15.000531,
					"end":	16.000595,
					"seconds":	1.0000640153884888,
					"bytes":	131072,
					"bits_per_second":	1048508.8792967579,
					"retransmits":	5,
					"snd_cwnd":	5792,
					"snd_wnd":	156672,
					"rtt":	111741,
					"rttvar":	20451,
					"pmtu":	1500,
					"omitted":	false,
					"sender":	true
				}],
			"sum":	{
				"start":	15.000531,
				"end":	16.000595,
				"seconds":	1.0000640153884888,
				"bytes":	131072,
				"bits_per_second":	1048508.8792967579,
				"retransmits":	5,
				"omitted":	false,
				"sender":	true
			}
		}, {
			"streams":	[{
					"socket":	5,
					"start":	16.000595,
					"end":	17.000517,
					"seconds":	0.999921977519989,
					"bytes":	0,
					"bits_per_second":	0,
					"retransmits":	3,
					"snd_cwnd":	7240,
					"snd_wnd":	156672,
					"rtt":	116754,
					"rttvar":	23010,
					"pmtu":	1500,
					"omitted":	false,
					"sender":	true
				}],
			"sum":	{
				"start":	16.000595,
				"end":	17.000517,
				"seconds":	0.999921977519989,
				"bytes":	0,
				"bits_per_second":	0,
				"retransmits":	3,
				"omitted":	false,
				"sender":	true
			}
		}, {
			"streams":	[{
					"socket":	5,
					"start":	17.000517,
					"end":	18.000533,
					"seconds":	1.0000159740448,
					"bytes":	131072,
					"bits_per_second":	1048559.2502675609,
					"retransmits":	0,
					"snd_cwnd":	13032,
					"snd_wnd":	156672,
					"rtt":	109720,
					"rttvar":	15835,
					"pmtu":	1500,
					"omitted":	false,
					"sender":	true
				}],
			"sum":	{
				"start":	17.000517,
				"end":	18.000533,
				"seconds":	1.0000159740448,
				"bytes":	131072,
				"bits_per_second":	1048559.2502675609,
				"retransmits":	0,
				"omitted":	false,
				"sender":	true
			}
		}, {
			"streams":	[{
					"socket":	5,
					"start":	18.000533,
					"end":	19.000593,
					"seconds":	1.000059962272644,
					"bytes":	131072,
					"bits_per_second":	1048513.1287699018,
					"retransmits":	3,
					"snd_cwnd":	14480,
					"snd_wnd":	156672,
					"rtt":	106402,
					"rttvar":	11702,
					"pmtu":	1500,
					"omitted":	false,
					"sender":	true
				}],
			"sum":	{
				"start":	18.000533,
				"end":	19.000593,
				"seconds":	1.000059962272644,
				"bytes":	131072,
				"bits_per_second":	1048513.1287699018,
				"retransmits":	3,
				"omitted":	false,
				"sender":	true
			}
		}, {
			"streams":	[{
					"socket":	5,
					"start":	19.000593,
					"end":	20.000535,
					"seconds":	0.99994200468063354,
					"bytes":	131072,
					"bits_per_second":	1048636.816027045,
					"retransmits":	0,
					"snd_cwnd":	18824,
					"snd_wnd":	156672,
					"rtt":	105268,
					"rttvar":	11325,
					"pmtu":	1500,
					"omitted":	false,
					"sender":	true
				}],
			"sum":	{
				"start":	19.000593,
				"end":	20.000535,
				"seconds":	0.99994200468063354,
				"bytes":	131072,
				"bits_per_second":	1048636.816027045,
				"retransmits":	0,
				"omitted":	false,
				"sender":	true
			}
		}, {
			"streams":	[{
					"socket":	5,
					"start":	20.000535,
					"end":	21.000516,
					"seconds":	0.99998098611831665,
					"bytes":	131072,
					"bits_per_second":	1048595.9378790965,
					"retransmits":	4,
					"snd_cwnd":	18824,
					"snd_wnd":	156672,
					"rtt":	101364,
					"rttvar":	4649,
					"pmtu":	1500,
					"omitted":	false,
					"sender":	true
				}],
			"sum":	{
				"start":	20.000535,
				"end":	21.000516,
				"seconds":	0.99998098611831665,
				"bytes":	131072,
				"bits_per_second":	1048595.9378790965,
				"retransmits":	4,
				"omitted":	false,
				"sender":	true
			}
		}, {
			"streams":	[{
					"socket":	5,
					"start":	21.000516,
					"end":	22.000117,
					"seconds":	0.99960100650787354,
					"bytes":	131072,
					"bits_per_second":	1048994.5419955323,
					"retransmits":	4,
					"snd_cwnd":	11584,
					"snd_wnd":	155136,
					"rtt":	107349,
					"rttvar":	13912,
					"pmtu":	1500,
					"omitted":	false,
					"sender":	true
				}],
			"sum":	{
				"start":	21.000516,
				"end":	22.000117,
				"seconds":	0.99960100650787354,
				"bytes":	131072,
				"bits_per_second":	1048994.5419955323,
				"retransmits":	4,
				"omitted":	false,
				"sender":	true
			}
		}, {
			"streams":	[{
					"socket":	5,
					"start":	22.000117,
					"end":	23.0006,
					"seconds":	1.00048303604126,
					"bytes":	131072,
					"bits_per_second":	1048069.7445396334,
					"retransmits":	3,
					"snd_cwnd":	7240,
					"snd_wnd":	156672,
					"rtt":	109751,
					"rttvar":	16506,
					"pmtu":	1500,
					"omitted":	false,
					"sender":	true
				}],
			"sum":	{
				"start":	22.000117,
				"end":	23.0006,
				"seconds":	1.00048303604126,
				"bytes":	131072,
				"bits_per_second":	1048069.7445396334,
				"retransmits":	3,
				"omitted":	false,
				"sender":	true
			}
		}, {
			"streams":	[{
					"socket":	5,
					"start":	23.0006,
					"end":	24.000524,
					"seconds":	0.99992400407791138,
					"bytes":	131072,
					"bits_per_second":	1048655.6935563853,
					"retransmits":	2,
					"snd_cwnd":	10136,
					"snd_wnd":	155136,
					"rtt":	106565,
					"rttvar":	11255,
					"pmtu":	1500,
					"omitted":	false,
					"sender":	true
				}],
			"sum":	{
				"start":	23.0006,
				"end":	24.000524,
				"seconds":	0.99992400407791138,
				"bytes":	131072,
				"bits_per_second":	1048655.6935563853,
				"retransmits":	2,
				"omitted":	false,
				"sender":	true
			}
		}, {
			"streams":	[{
					"socket":	5,
					"start":	24.000524,
					"end":	25.000526,
					"seconds":	1.0000020265579224,
					"bytes":	0,
					"bits_per_second":	0,
					"retransmits":	2,
					"snd_cwnd":	10136,
					"snd_wnd":	156672,
					"rtt":	110920,
					"rttvar":	18074,
					"pmtu":	1500,
					"omitted":	false,
					"sender":	true
				}],
			"sum":	{
				"start":	24.000524,
				"end":	25.000526,
				"seconds":	1.0000020265579224,
				"bytes":	0,
				"bits_per_second":	0,
				"retransmits":	2,
				"omitted":	false,
				"sender":	true
			}
		}, {
			"streams":	[{
					"socket":	5,
					"start":	25.000526,
					"end":	26.000538,
					"seconds":	1.0000120401382446,
					"bytes":	131072,
					"bits_per_second":	1048563.3751520049,
					"retransmits":	2,
					"snd_cwnd":	10136,
					"snd_wnd":	156672,
					"rtt":	107380,
					"rttvar":	15436,
					"pmtu":	1500,
					"omitted":	false,
					"sender":	true
				}],
			"sum":	{
				"start":	25.000526,
				"end":	26.000538,
				"seconds":	1.0000120401382446,
				"bytes":	131072,
				"bits_per_second":	1048563.3751520049,
				"retransmits":	2,
				"omitted":	false,
				"sender":	true
			}
		}, {
			"streams":	[{
					"socket":	5,
					"start":	26.000538,
					"end":	27.000596,
					"seconds":	1.0000580549240112,
					"bytes":	131072,
					"bits_per_second":	1048515.1285338884,
					"retransmits":	0,
					"snd_cwnd":	17376,
					"snd_wnd":	156672,
					"rtt":	104663,
					"rttvar":	6620,
					"pmtu":	1500,
					"omitted":	false,
					"sender":	true
				}],
			"sum":	{
				"start":	26.000538,
				"end":	27.000596,
				"seconds":	1.0000580549240112,
				"bytes":	131072,
				"bits_per_second":	1048515.1285338884,
				"retransmits":	0,
				"omitted":	false,
				"sender":	true
			}
		}, {
			"streams":	[{
					"socket":	5,
					"start":	27.000596,
					"end":	28.000526,
					"seconds":	0.99993002414703369,
					"bytes":	131072,
					"bits_per_second":	1048649.3801348375,
					"retransmits":	4,
					"snd_cwnd":	10136,
					"snd_wnd":	153728,
					"rtt":	98892,
					"rttvar":	1719,
					"pmtu":	1500,
					"omitted":	false,
					"sender":	true
				}],
			"sum":	{
				"start":	27.000596,
				"end":	28.000526,
				"seconds":	0.99993002414703369,
				"bytes":	131072,
				"bits_per_second":	1048649.3801348375,
				"retransmits":	4,
				"omitted":	false,
				"sender":	true
			}
		}, {
			"streams":	[{
					"socket":	5,
					"start":	28.000526,
					"end":	29.000557,
					"seconds":	1.0000309944152832,
					"bytes":	131072,
					"bits_per_second":	1048543.5010072873,
					"retransmits":	4,
					"snd_cwnd":	7240,
					"snd_wnd":	156672,
					"rtt":	104279,
					"rttvar":	8281,
					"pmtu":	1500,
					"omitted":	false,
					"sender":	true
				}],
			"sum":	{
				"start":	28.000526,
				"end":	29.000557,
				"seconds":	1.0000309944152832,
				"bytes":	131072,
				"bits_per_second":	1048543.5010072873,
				"retransmits":	4,
				"omitted":	false,
				"sender":	true
			}
		}, {
			"streams":	[{
					"socket":	5,
					"start":	29.000557,
					"end":	30.001263,
					"seconds":	1.00070595741272,
					"bytes":	131072,
					"bits_per_second":	1047836.2722163122,
					"retransmits":	2,
					"snd_cwnd":	8688,
					"snd_wnd":	156672,
					"rtt":	103985,
					"rttvar":	9617,
					"pmtu":	1500,
					"omitted":	false,
					"sender":	true
				}],
			"sum":	{
				"start":	29.000557,
				"end":	30.001263,
				"seconds":	1.00070595741272,
				"bytes":	131072,
				"bits_per_second":	1047836.2722163122,
				"retransmits":	2,
				"omitted":	false,
				"sender":	true
			}
		}],
	"end":	{
		"streams":	[{
				"sender":	{
					"socket":	5,
					"start":	0,
					"end":	30.001263,
					"seconds":	30.001263,
					"bytes":	3145728,
					"bits_per_second":	838825.48544706265,
					"retransmits":	78,
					"max_snd_cwnd":	18824,
					"max_snd_wnd":	156672,
					"max_rtt":	117692,
					"min_rtt":	98892,
					"mean_rtt":	106518,
					"sender":	true
				},
				"receiver":	{
					"socket":	5,
					"start":	0,
					"end":	30.089174,
					"seconds":	30.001263,
					"bytes":	3014656,
					"bits_per_second":	801525.758068334,
					"sender":	true
				}
			}],
		"sum_sent":	{
			"start":	0,
			"end":	30.001263,
			"seconds":	30.001263,
			"bytes":	3145728,
			"bits_per_second":	838825.48544706265,
			"retransmits":	78,
			"sender":	true
		},
		"sum_received":	{
			"start":	0,
			"end":	30.089174,
			"seconds":	30.089174,
			"bytes":	3014656,
			"bits_per_second":	801525.758068334,
			"sender":	true
		},
		"cpu_utilization_percent":	{
			"host_total":	3.0142209923982,
			"host_user":	0.86184131912452078,
			"host_system":	2.1523730896333011,
			"remote_total":	0.21713776827240824,
			"remote_user":	0.036215661756553649,
			"remote_system":	0.18092210651585461
		},
		"sender_tcp_congestion":	"cubic",
		"receiver_tcp_congestion":	"cubic"
	}
}
